{"is_source_file": true, "file_id": 88, "git_revision": "2676c3675909df2fe5419eb40f5227e95189e0be", "state": 1, "description": "", "external_files": [], "external_methods": [], "published": [], "classes": [], "methods": [], "calls": [], "search-terms": [], "ctags": [{"_type": "tag", "name": "NotFound", "path": "/home/kavia/workspace/code-generation/healthify-wellness-companion-38752-38761/healthify_frontend/src/pages/NotFound.jsx", "pattern": "/^export default function NotFound() {$/", "language": "JavaScript", "kind": "function", "signature": "()"}], "format": "JavaScript", "hash": "f8574155dc9872ef2bd66b6f9e535075", "format-version": 4, "code-base-name": "healthify_frontend", "filename": "healthify_frontend/src/pages/NotFound.jsx", "knowledge_revision": 142}